client_/__init__.py
client_/add_contact.py
client_/database.py
client_/del_contact.py
client_/main_window.py
client_/main_window_conv.py
client_/start_dialog.py
client_/transport.py
common/__init__.py
common/utils.py
common/variables.py
logs/__init__.py
logs/config_client_log.py
logs/config_server_log.py
unit_tests/__init__.py
unit_tests/test_client.py
unit_tests/test_utils.py
py_messenger_client_by_maxg-0.1.1.dist-info/METADATA
py_messenger_client_by_maxg-0.1.1.dist-info/WHEEL
py_messenger_client_by_maxg-0.1.1.dist-info/top_level.txt
py_messenger_client_by_maxg-0.1.1.dist-info/RECORD
