Metadata-Version: 2.1
Name: py-messenger-client-by-maxg
Version: 0.1.1
Summary: Messenger Client
Home-page: UNKNOWN
Author: IMaximGubanov
Author-email: max.gubanov@vk.com
License: UNKNOWN
Platform: UNKNOWN
Requires-Dist: PyQt5
Requires-Dist: pycryptodome
Requires-Dist: pycryptodomex
Requires-Dist: sqlalchemy
